odoo/addons/sale_order_import/README.rst
odoo/addons/sale_order_import/__init__.py
odoo/addons/sale_order_import/__manifest__.py
odoo/addons/sale_order_import/i18n/es.po
odoo/addons/sale_order_import/i18n/fr.po
odoo/addons/sale_order_import/i18n/sale_order_import.pot
odoo/addons/sale_order_import/models/__init__.py
odoo/addons/sale_order_import/models/sale.py
odoo/addons/sale_order_import/readme/CONTRIBUTORS.rst
odoo/addons/sale_order_import/readme/DESCRIPTION.rst
odoo/addons/sale_order_import/readme/USAGE.rst
odoo/addons/sale_order_import/static/description/icon.png
odoo/addons/sale_order_import/static/description/index.html
odoo/addons/sale_order_import/tests/__init__.py
odoo/addons/sale_order_import/tests/test_order_import.py
odoo/addons/sale_order_import/tests/test_sale_order.py
odoo/addons/sale_order_import/wizard/__init__.py
odoo/addons/sale_order_import/wizard/sale_order_import.py
odoo/addons/sale_order_import/wizard/sale_order_import_view.xml
odoo11_addon_sale_order_import-11.0.1.0.0.99.dev6.dist-info/METADATA
odoo11_addon_sale_order_import-11.0.1.0.0.99.dev6.dist-info/WHEEL
odoo11_addon_sale_order_import-11.0.1.0.0.99.dev6.dist-info/top_level.txt
odoo11_addon_sale_order_import-11.0.1.0.0.99.dev6.dist-info/RECORD
